iterprod/__init__.py
iterprod/__main__.py
iterprod/core/__init__.py
iterprod/tests/__init__.py
iterprod/tests/test_1984.py
iterprod-1.0.2.dist-info/licenses/LICENSE.txt
iterprod-1.0.2.dist-info/METADATA
iterprod-1.0.2.dist-info/WHEEL
iterprod-1.0.2.dist-info/top_level.txt
iterprod-1.0.2.dist-info/RECORD
