Metadata-Version: 2.4
Name: iterprod
Version: 1.0.2
Summary: This project provides a faster python-only alternative to itertools.product.
Author-email: Johannes <johannes.programming@gmail.com>
License: The MIT License (MIT)
Project-URL: Download, https://pypi.org/project/iterprod/#files
Project-URL: Index, https://pypi.org/project/iterprod/
Project-URL: Source, https://github.com/johannes-programming/iterprod/
Project-URL: Website, https://iterprod.johannes-programming.online/
Classifier: Development Status :: 5 - Production/Stable
Classifier: License :: OSI Approved :: MIT License
Classifier: Natural Language :: English
Classifier: Operating System :: OS Independent
Classifier: Programming Language :: Python
Classifier: Programming Language :: Python :: 3
Classifier: Programming Language :: Python :: 3 :: Only
Classifier: Typing :: Typed
Requires-Python: >=3.11
License-File: LICENSE.txt
Dynamic: license-file
